README.md
setup.py
ank_gauss_distribution/Binomialdistribution.py
ank_gauss_distribution/Gaussiandistribution.py
ank_gauss_distribution/Generaldistribution.py
ank_gauss_distribution/__init__.py
ank_gauss_distribution.egg-info/PKG-INFO
ank_gauss_distribution.egg-info/SOURCES.txt
ank_gauss_distribution.egg-info/dependency_links.txt
ank_gauss_distribution.egg-info/not-zip-safe
ank_gauss_distribution.egg-info/top_level.txt