Metadata-Version: 1.0
Name: ank-gauss-distribution
Version: 1.0
Summary: ank_gauss_distribution
Home-page: UNKNOWN
Author: UNKNOWN
Author-email: UNKNOWN
License: UNKNOWN
Platform: UNKNOWN
